CHANGES.rst
LICENSE
MANIFEST.in
README.rst
setup.py
thetaexif/__init__.py
thetaexif/__main__.py
thetaexif/cli.py
thetaexif/exif.py
thetaexif/projection.py
thetaexif/tag.py
thetaexif.egg-info/PKG-INFO
thetaexif.egg-info/SOURCES.txt
thetaexif.egg-info/dependency_links.txt
thetaexif.egg-info/entry_points.txt
thetaexif.egg-info/requires.txt
thetaexif.egg-info/top_level.txt