Metadata-Version: 1.1
Name: thetaexif
Version: 0.2
Summary: THETA EXIF Library
Home-page: https://github.com/regen100/thetaexif
Author: Regen
Author-email: git@exadge.com
License: MIT
Platform: any
Classifier: Development Status :: 3 - Alpha
Classifier: Intended Audience :: Developers
Classifier: Intended Audience :: End Users/Desktop
Classifier: Environment :: Console
Classifier: License :: OSI Approved :: MIT License
Classifier: Operating System :: OS Independent
Classifier: Topic :: Utilities
Classifier: Programming Language :: Python :: 3.6
Classifier: Programming Language :: Python :: 3.7
